LICENSE
MANIFEST.in
README.md
setup.py
granary/__init__.py
granary/as1.py
granary/as2.py
granary/atom.py
granary/bluesky.py
granary/facebook.py
granary/flickr.py
granary/github.py
granary/instagram.py
granary/jsonfeed.py
granary/mastodon.py
granary/meetup.py
granary/microformats2.py
granary/nostr.py
granary/pixelfed.py
granary/reddit.py
granary/rss.py
granary/source.py
granary/twitter.py
granary.egg-info/PKG-INFO
granary.egg-info/SOURCES.txt
granary.egg-info/dependency_links.txt
granary.egg-info/requires.txt
granary.egg-info/top_level.txt
granary/templates/_entry.atom
granary/templates/author.atom
granary/templates/entry.atom
granary/templates/host-meta.jrd
granary/templates/host-meta.xrd
granary/templates/host-meta.xrds
granary/templates/index.html
granary/templates/user_feed.atom
granary/tests/__init__.py
granary/tests/test_as1.py
granary/tests/test_as2.py
granary/tests/test_atom.py
granary/tests/test_bluesky.py
granary/tests/test_facebook.py
granary/tests/test_flickr.py
granary/tests/test_github.py
granary/tests/test_instagram.py
granary/tests/test_jsonfeed.py
granary/tests/test_mastodon.py
granary/tests/test_meetup.py
granary/tests/test_microformats2.py
granary/tests/test_nostr.py
granary/tests/test_pixelfed.py
granary/tests/test_reddit.py
granary/tests/test_rss.py
granary/tests/test_source.py
granary/tests/test_testdata.py
granary/tests/test_twitter.py
granary/tests/testdata/accept_follow.as.json
granary/tests/testdata/accept_follow.as2.json
granary/tests/testdata/activity_with_actor.as-from-as2.json
granary/tests/testdata/activity_with_actor.as2.json
granary/tests/testdata/activity_with_person_tag.as.json
granary/tests/testdata/activity_with_person_tag.as.mf2.html
granary/tests/testdata/activity_with_person_tag.as.mf2.json
granary/tests/testdata/activity_with_person_tag.as2.json
granary/tests/testdata/actor.as-from-bsky.json
granary/tests/testdata/actor.as.json
granary/tests/testdata/actor.as2.json
granary/tests/testdata/actor.bsky.json
granary/tests/testdata/actor.mf2.html
granary/tests/testdata/actor.mf2.json
granary/tests/testdata/actor_multiple_urls.mf2.html
