Metadata-Version: 2.1
Name: granary
Version: 9.0
Summary: The social web translator
Home-page: https://github.com/snarfed/granary
Author: Ryan Barrett
Author-email: granary@ryanb.org
License: Public domain
Keywords: social facebook flickr github instagram twitter activitystreams html microformats2 meetup mf2 atom rss jsonfeed
Classifier: Development Status :: 5 - Production/Stable
Classifier: Intended Audience :: Developers
Classifier: Environment :: Web Environment
Classifier: License :: OSI Approved :: MIT License
Classifier: License :: Public Domain
Classifier: Programming Language :: Python :: 3
Classifier: Programming Language :: Python :: 3.7
Classifier: Programming Language :: Python :: 3.8
Classifier: Programming Language :: Python :: 3.9
Classifier: Topic :: Software Development :: Libraries :: Python Modules
Requires-Python: >=3.7
License-File: LICENSE
Requires-Dist: beautifulsoup4>=4.8
Requires-Dist: bech32
Requires-Dist: brevity>=0.2.17
Requires-Dist: feedgen>=0.9
Requires-Dist: feedparser
Requires-Dist: html2text>=2019.8.11
Requires-Dist: humanfriendly>=4.18
Requires-Dist: jinja2>=2.10
Requires-Dist: lexrpc>=0.2
Requires-Dist: mf2util>=0.5.0
Requires-Dist: multiformats>=0.3.1
Requires-Dist: oauth-dropins>=6.8
Requires-Dist: pillow
Requires-Dist: praw>=7.3.0
Requires-Dist: python-dateutil>=2.8
Requires-Dist: requests>=2.22
Requires-Dist: secp256k1>=0.14.0
Requires-Dist: websockets>=11.0
